{
  "Barbarian": {
    "primary": "Strength",
    "secondary": "Consitution"
  },
  "Bard": {
    "primary": "Charisma",
    "secondary": "Dexterity"
  },
  "Cleric": {
    "primary": "Wisdom",
    "secondary": "Charisma"
  },
  "Druid": {
    "primary": "Wisdom",
    "secondary": "Intelligence"
  },
  "Fighter": {
    "primary": "Strength",
    "alternative": "Dexterity",
    "secondary": "Consitution"
  },
  "Monk": {
    "primary": "Dexterity",
    "cooperative": "Wisdom",
    "secondary": "Strength"
  },
  "Paladin": {
    "primary": "Strength",
    "cooperative": "Charisma",
    "secondary": "Wisdom"
  },
  "Ranger": {
    "primary": "Dexterity",
    "cooperative": "Wisdom",
    "secondary": "Strength"
  },
  "Rogue": {
    "primary": "Dexterity",
    "secondary": "Intelligence"
  },
  "Sorcerer": {
    "primary": "Charisma",
    "secondary": "Consitution"
  },
  "Warlock": {
    "primary": "Charisma",
    "secondary": "Wisdom"
  },
  "Wizard": {
    "primary": "Intelligence",
    "secondary": "Wisdom"
  }
}